{"nodes": [{"id": "c_users_urbra_onedrive_desktop_projects_zoom_tracking_modules_user_interaction_py", "label": "user_interaction.py", "file_type": "code", "source_file": "C:\\Users\\urbra\\OneDrive\\Desktop\\Projects\\zoom-tracking\\modules\\user_interaction.py", "source_location": "L1"}, {"id": "user_interaction_userinteractionmodule", "label": "UserInteractionModule", "file_type": "code", "source_file": "C:\\Users\\urbra\\OneDrive\\Desktop\\Projects\\zoom-tracking\\modules\\user_interaction.py", "source_location": "L44"}, {"id": "user_interaction_userinteractionmodule_init", "label": ".__init__()", "file_type": "code", "source_file": "C:\\Users\\urbra\\OneDrive\\Desktop\\Projects\\zoom-tracking\\modules\\user_interaction.py", "source_location": "L45"}, {"id": "user_interaction_userinteractionmodule_register_mouse_callback", "label": ".register_mouse_callback()", "file_type": "code", "source_file": "C:\\Users\\urbra\\OneDrive\\Desktop\\Projects\\zoom-tracking\\modules\\user_interaction.py", "source_location": "L54"}, {"id": "user_interaction_userinteractionmodule_on_mouse", "label": "._on_mouse()", "file_type": "code", "source_file": "C:\\Users\\urbra\\OneDrive\\Desktop\\Projects\\zoom-tracking\\modules\\user_interaction.py", "source_location": "L58"}, {"id": "user_interaction_userinteractionmodule_process_click", "label": ".process_click()", "file_type": "code", "source_file": "C:\\Users\\urbra\\OneDrive\\Desktop\\Projects\\zoom-tracking\\modules\\user_interaction.py", "source_location": "L64"}, {"id": "user_interaction_userinteractionmodule_check_track_alive", "label": ".check_track_alive()", "file_type": "code", "source_file": "C:\\Users\\urbra\\OneDrive\\Desktop\\Projects\\zoom-tracking\\modules\\user_interaction.py", "source_location": "L113"}, {"id": "user_interaction_userinteractionmodule_needs_selection", "label": ".needs_selection()", "file_type": "code", "source_file": "C:\\Users\\urbra\\OneDrive\\Desktop\\Projects\\zoom-tracking\\modules\\user_interaction.py", "source_location": "L131"}, {"id": "user_interaction_userinteractionmodule_draw_ui_hints", "label": ".draw_ui_hints()", "file_type": "code", "source_file": "C:\\Users\\urbra\\OneDrive\\Desktop\\Projects\\zoom-tracking\\modules\\user_interaction.py", "source_location": "L135"}, {"id": "user_interaction_userinteractionmodule_reset_selection", "label": ".reset_selection()", "file_type": "code", "source_file": "C:\\Users\\urbra\\OneDrive\\Desktop\\Projects\\zoom-tracking\\modules\\user_interaction.py", "source_location": "L155"}, {"id": "user_interaction_dist2", "label": "_dist2()", "file_type": "code", "source_file": "C:\\Users\\urbra\\OneDrive\\Desktop\\Projects\\zoom-tracking\\modules\\user_interaction.py", "source_location": "L164"}, {"id": "user_interaction_rationale_1", "label": "Module 4 \u2014 User Interaction ============================ Handles all user input:", "file_type": "rationale", "source_file": "C:\\Users\\urbra\\OneDrive\\Desktop\\Projects\\zoom-tracking\\modules\\user_interaction.py", "source_location": "L1"}, {"id": "user_interaction_rationale_55", "label": "Attach mouse handler.  Call after cv2.namedWindow() has been created.", "file_type": "rationale", "source_file": "C:\\Users\\urbra\\OneDrive\\Desktop\\Projects\\zoom-tracking\\modules\\user_interaction.py", "source_location": "L55"}, {"id": "user_interaction_rationale_65", "label": "Consume any pending click and resolve it to the best matching track.          Sh", "file_type": "rationale", "source_file": "C:\\Users\\urbra\\OneDrive\\Desktop\\Projects\\zoom-tracking\\modules\\user_interaction.py", "source_location": "L65"}, {"id": "user_interaction_rationale_114", "label": "Returns True if the currently selected track is still active.         Sets the r", "file_type": "rationale", "source_file": "C:\\Users\\urbra\\OneDrive\\Desktop\\Projects\\zoom-tracking\\modules\\user_interaction.py", "source_location": "L114"}, {"id": "user_interaction_rationale_136", "label": "Render instruction banner at the bottom of the frame (in-place).", "file_type": "rationale", "source_file": "C:\\Users\\urbra\\OneDrive\\Desktop\\Projects\\zoom-tracking\\modules\\user_interaction.py", "source_location": "L136"}, {"id": "user_interaction_rationale_156", "label": "Externally force re-selection (e.g. via 'R' key).", "file_type": "rationale", "source_file": "C:\\Users\\urbra\\OneDrive\\Desktop\\Projects\\zoom-tracking\\modules\\user_interaction.py", "source_location": "L156"}, {"id": "user_interaction_rationale_165", "label": "Squared Euclidean distance \u2014 avoids sqrt for comparison.", "file_type": "rationale", "source_file": "C:\\Users\\urbra\\OneDrive\\Desktop\\Projects\\zoom-tracking\\modules\\user_interaction.py", "source_location": "L165"}], "edges": [{"source": "c_users_urbra_onedrive_desktop_projects_zoom_tracking_modules_user_interaction_py", "target": "cv2", "relation": "imports", "confidence": "EXTRACTED", "source_file": "C:\\Users\\urbra\\OneDrive\\Desktop\\Projects\\zoom-tracking\\modules\\user_interaction.py", "source_location": "L35", "weight": 1.0}, {"source": "c_users_urbra_onedrive_desktop_projects_zoom_tracking_modules_user_interaction_py", "target": "numpy", "relation": "imports", "confidence": "EXTRACTED", "source_file": "C:\\Users\\urbra\\OneDrive\\Desktop\\Projects\\zoom-tracking\\modules\\user_interaction.py", "source_location": "L36", "weight": 1.0}, {"source": "c_users_urbra_onedrive_desktop_projects_zoom_tracking_modules_user_interaction_py", "target": "typing", "relation": "imports_from", "confidence": "EXTRACTED", "source_file": "C:\\Users\\urbra\\OneDrive\\Desktop\\Projects\\zoom-tracking\\modules\\user_interaction.py", "source_location": "L37", "weight": 1.0}, {"source": "c_users_urbra_onedrive_desktop_projects_zoom_tracking_modules_user_interaction_py", "target": "c_users_urbra_onedrive_desktop_projects_zoom_tracking_modules_tracker_py", "relation": "imports_from", "confidence": "EXTRACTED", "source_file": "C:\\Users\\urbra\\OneDrive\\Desktop\\Projects\\zoom-tracking\\modules\\user_interaction.py", "source_location": "L38", "weight": 1.0}, {"source": "c_users_urbra_onedrive_desktop_projects_zoom_tracking_modules_user_interaction_py", "target": "user_interaction_userinteractionmodule", "relation": "contains", "confidence": "EXTRACTED", "source_file": "C:\\Users\\urbra\\OneDrive\\Desktop\\Projects\\zoom-tracking\\modules\\user_interaction.py", "source_location": "L44", "weight": 1.0}, {"source": "user_interaction_userinteractionmodule", "target": "user_interaction_userinteractionmodule_init", "relation": "method", "confidence": "EXTRACTED", "source_file": "C:\\Users\\urbra\\OneDrive\\Desktop\\Projects\\zoom-tracking\\modules\\user_interaction.py", "source_location": "L45", "weight": 1.0}, {"source": "user_interaction_userinteractionmodule", "target": "user_interaction_userinteractionmodule_register_mouse_callback", "relation": "method", "confidence": "EXTRACTED", "source_file": "C:\\Users\\urbra\\OneDrive\\Desktop\\Projects\\zoom-tracking\\modules\\user_interaction.py", "source_location": "L54", "weight": 1.0}, {"source": "user_interaction_userinteractionmodule", "target": "user_interaction_userinteractionmodule_on_mouse", "relation": "method", "confidence": "EXTRACTED", "source_file": "C:\\Users\\urbra\\OneDrive\\Desktop\\Projects\\zoom-tracking\\modules\\user_interaction.py", "source_location": "L58", "weight": 1.0}, {"source": "user_interaction_userinteractionmodule", "target": "user_interaction_userinteractionmodule_process_click", "relation": "method", "confidence": "EXTRACTED", "source_file": "C:\\Users\\urbra\\OneDrive\\Desktop\\Projects\\zoom-tracking\\modules\\user_interaction.py", "source_location": "L64", "weight": 1.0}, {"source": "user_interaction_userinteractionmodule", "target": "user_interaction_userinteractionmodule_check_track_alive", "relation": "method", "confidence": "EXTRACTED", "source_file": "C:\\Users\\urbra\\OneDrive\\Desktop\\Projects\\zoom-tracking\\modules\\user_interaction.py", "source_location": "L113", "weight": 1.0}, {"source": "user_interaction_userinteractionmodule", "target": "user_interaction_userinteractionmodule_needs_selection", "relation": "method", "confidence": "EXTRACTED", "source_file": "C:\\Users\\urbra\\OneDrive\\Desktop\\Projects\\zoom-tracking\\modules\\user_interaction.py", "source_location": "L131", "weight": 1.0}, {"source": "user_interaction_userinteractionmodule", "target": "user_interaction_userinteractionmodule_draw_ui_hints", "relation": "method", "confidence": "EXTRACTED", "source_file": "C:\\Users\\urbra\\OneDrive\\Desktop\\Projects\\zoom-tracking\\modules\\user_interaction.py", "source_location": "L135", "weight": 1.0}, {"source": "user_interaction_userinteractionmodule", "target": "user_interaction_userinteractionmodule_reset_selection", "relation": "method", "confidence": "EXTRACTED", "source_file": "C:\\Users\\urbra\\OneDrive\\Desktop\\Projects\\zoom-tracking\\modules\\user_interaction.py", "source_location": "L155", "weight": 1.0}, {"source": "c_users_urbra_onedrive_desktop_projects_zoom_tracking_modules_user_interaction_py", "target": "user_interaction_dist2", "relation": "contains", "confidence": "EXTRACTED", "source_file": "C:\\Users\\urbra\\OneDrive\\Desktop\\Projects\\zoom-tracking\\modules\\user_interaction.py", "source_location": "L164", "weight": 1.0}, {"source": "user_interaction_userinteractionmodule_process_click", "target": "user_interaction_dist2", "relation": "calls", "confidence": "EXTRACTED", "source_file": "C:\\Users\\urbra\\OneDrive\\Desktop\\Projects\\zoom-tracking\\modules\\user_interaction.py", "source_location": "L88", "weight": 1.0}, {"source": "user_interaction_rationale_1", "target": "c_users_urbra_onedrive_desktop_projects_zoom_tracking_modules_user_interaction_py", "relation": "rationale_for", "confidence": "EXTRACTED", "source_file": "C:\\Users\\urbra\\OneDrive\\Desktop\\Projects\\zoom-tracking\\modules\\user_interaction.py", "source_location": "L1", "weight": 1.0}, {"source": "user_interaction_rationale_55", "target": "user_interaction_userinteractionmodule_register_mouse_callback", "relation": "rationale_for", "confidence": "EXTRACTED", "source_file": "C:\\Users\\urbra\\OneDrive\\Desktop\\Projects\\zoom-tracking\\modules\\user_interaction.py", "source_location": "L55", "weight": 1.0}, {"source": "user_interaction_rationale_65", "target": "user_interaction_userinteractionmodule_process_click", "relation": "rationale_for", "confidence": "EXTRACTED", "source_file": "C:\\Users\\urbra\\OneDrive\\Desktop\\Projects\\zoom-tracking\\modules\\user_interaction.py", "source_location": "L65", "weight": 1.0}, {"source": "user_interaction_rationale_114", "target": "user_interaction_userinteractionmodule_check_track_alive", "relation": "rationale_for", "confidence": "EXTRACTED", "source_file": "C:\\Users\\urbra\\OneDrive\\Desktop\\Projects\\zoom-tracking\\modules\\user_interaction.py", "source_location": "L114", "weight": 1.0}, {"source": "user_interaction_rationale_136", "target": "user_interaction_userinteractionmodule_draw_ui_hints", "relation": "rationale_for", "confidence": "EXTRACTED", "source_file": "C:\\Users\\urbra\\OneDrive\\Desktop\\Projects\\zoom-tracking\\modules\\user_interaction.py", "source_location": "L136", "weight": 1.0}, {"source": "user_interaction_rationale_156", "target": "user_interaction_userinteractionmodule_reset_selection", "relation": "rationale_for", "confidence": "EXTRACTED", "source_file": "C:\\Users\\urbra\\OneDrive\\Desktop\\Projects\\zoom-tracking\\modules\\user_interaction.py", "source_location": "L156", "weight": 1.0}, {"source": "user_interaction_rationale_165", "target": "user_interaction_dist2", "relation": "rationale_for", "confidence": "EXTRACTED", "source_file": "C:\\Users\\urbra\\OneDrive\\Desktop\\Projects\\zoom-tracking\\modules\\user_interaction.py", "source_location": "L165", "weight": 1.0}], "raw_calls": [{"caller_nid": "user_interaction_userinteractionmodule_register_mouse_callback", "callee": "setMouseCallback", "source_file": "C:\\Users\\urbra\\OneDrive\\Desktop\\Projects\\zoom-tracking\\modules\\user_interaction.py", "source_location": "L56"}, {"caller_nid": "user_interaction_userinteractionmodule_process_click", "callee": "float", "source_file": "C:\\Users\\urbra\\OneDrive\\Desktop\\Projects\\zoom-tracking\\modules\\user_interaction.py", "source_location": "L81"}, {"caller_nid": "user_interaction_userinteractionmodule_process_click", "callee": "min", "source_file": "C:\\Users\\urbra\\OneDrive\\Desktop\\Projects\\zoom-tracking\\modules\\user_interaction.py", "source_location": "L98"}, {"caller_nid": "user_interaction_userinteractionmodule_draw_ui_hints", "callee": "copy", "source_file": "C:\\Users\\urbra\\OneDrive\\Desktop\\Projects\\zoom-tracking\\modules\\user_interaction.py", "source_location": "L145"}, {"caller_nid": "user_interaction_userinteractionmodule_draw_ui_hints", "callee": "rectangle", "source_file": "C:\\Users\\urbra\\OneDrive\\Desktop\\Projects\\zoom-tracking\\modules\\user_interaction.py", "source_location": "L146"}, {"caller_nid": "user_interaction_userinteractionmodule_draw_ui_hints", "callee": "addWeighted", "source_file": "C:\\Users\\urbra\\OneDrive\\Desktop\\Projects\\zoom-tracking\\modules\\user_interaction.py", "source_location": "L147"}, {"caller_nid": "user_interaction_userinteractionmodule_draw_ui_hints", "callee": "putText", "source_file": "C:\\Users\\urbra\\OneDrive\\Desktop\\Projects\\zoom-tracking\\modules\\user_interaction.py", "source_location": "L148"}]}